django_builder/__init__.py
django_builder/apps.py
django_builder/management/__init__.py
cli_django_builder-0.1.0.dist-info/LICENSE
cli_django_builder-0.1.0.dist-info/METADATA
cli_django_builder-0.1.0.dist-info/WHEEL
cli_django_builder-0.1.0.dist-info/top_level.txt
cli_django_builder-0.1.0.dist-info/RECORD
