Metadata-Version: 2.1
Name: cli-django-builder
Version: 0.1.0
Summary: A command line interface to build Django application and RESTful application using DRF
Home-page: https://gitlab.com/frier17/django_builder.git
Author: https://gitlab.com/frier17/
Author-email: frier17@a17s.co.uk
License: MIT
Platform: UNKNOWN
Classifier: Development Status :: 3 - Alpha
Classifier: Intended Audience :: Developers
Classifier: Topic :: Software Development :: Build Tools
Classifier: License :: OSI Approved :: MIT License
Classifier: Programming Language :: Python :: 3
Classifier: Programming Language :: Python :: 3.8
